port_scanner_rq/__init__.py
port_scanner_rq/main.py
port_scanner_rq-1.1.2.dist-info/licenses/LICENSE
port_scanner_rq-1.1.2.dist-info/METADATA
port_scanner_rq-1.1.2.dist-info/WHEEL
port_scanner_rq-1.1.2.dist-info/top_level.txt
port_scanner_rq-1.1.2.dist-info/RECORD
