Metadata-Version: 2.4
Name: port_scanner_rq
Version: 1.1.2
Summary: A high-speed threaded TCP port scanner.
Author: xRangeroQ
Author-email: xRangeroQ@email.com
License: MIT
Requires-Python: >=3.6
License-File: LICENSE
Dynamic: author
Dynamic: author-email
Dynamic: description
Dynamic: description-content-type
Dynamic: license
Dynamic: license-file
Dynamic: requires-python
Dynamic: summary
